gino_quart.py
gino_quart-0.1.2.dist-info/entry_points.txt
gino_quart-0.1.2.dist-info/LICENSE
gino_quart-0.1.2.dist-info/WHEEL
gino_quart-0.1.2.dist-info/METADATA
gino_quart-0.1.2.dist-info/RECORD
