Metadata-Version: 2.1
Name: gino-quart
Version: 0.1.2
Summary: An extension for GINO to integrate with Quart
Home-page: https://github.com/python-gino/gino-quart
License: BSD-3-Clause
Keywords: sqlalchemy,python3,quart,gino
Author: Tony Wang
Author-email: wwwjfy@gmail.com
Requires-Python: >=3.7,<4.0
Classifier: Development Status :: 3 - Alpha
Classifier: Intended Audience :: Developers
Classifier: License :: OSI Approved :: BSD License
Classifier: Natural Language :: English
Classifier: Programming Language :: Python :: 3
Classifier: Programming Language :: Python :: 3.7
Classifier: Programming Language :: Python :: 3.8
Classifier: Programming Language :: Python :: 3.9
Requires-Dist: Quart (>=0.15.1,<0.16.0)
Requires-Dist: Werkzeug (>=2.0.1,<3.0.0)
Requires-Dist: gino (>=1.0.0rc2,<2.0.0)
Project-URL: Documentation, https://python-gino.org/docs/
Project-URL: Repository, https://github.com/python-gino/gino-quart
